{
"instructions_readme": "1) Open Chrome, 2) go to chrome://tracing, 3) click Load, 4) navigate to this file.",

"traceEvents":[
{ "pid": 1, "tid": 1, "ph": "M", "name": "thread_name", "args": { "name": "" } },
{ "pid": 1, "tid": 1, "ts": 1.5999999595806, "dur": 30649951.171875, "ph": "X", "name": "il2cpp.exe", "args": { "durationMS": 30649.951171875, "detail": "" } },
{ "pid": 1, "tid": 1, "ts": 69742.6986694336, "dur": 30577232.421875, "ph": "X", "name": "ConvertAssemblies", "args": { "durationMS": 30577.232421875, "detail": "" } },
{ "pid": 1, "tid": 1, "ts": 86364.3035888672, "dur": 524623.718261719, "ph": "X", "name": "Collect assemblies to convert", "args": { "durationMS": 524.623718261719, "detail": "" } },
{ "pid": 1, "tid": 1, "ts": 611121.215820313, "dur": 105126.998901367, "ph": "X", "name": "RegisterCorlib", "args": { "durationMS": 105.126998901367, "detail": "" } },
{ "pid": 1, "tid": 1, "ts": 716464.050292969, "dur": 54638.7023925781, "ph": "X", "name": "PreProcessIL", "args": { "durationMS": 54.6387023925781, "detail": "" } },
{ "pid": 1, "tid": 1, "ts": 716464.477539063, "dur": 8387.00008392334, "ph": "X", "name": "Inject base types and finalizers into COM and Windows Runtime types", "args": { "durationMS": 8.38700008392334, "detail": "" } },
{ "pid": 1, "tid": 1, "ts": 716683.898925781, "dur": 4522.09997177124, "ph": "X", "name": "ModifyCOMAndWindowsRuntimeTypes in assembly", "args": { "durationMS": 4.52209997177124, "detail": "mscorlib" } },
{ "pid": 1, "tid": 1, "ts": 722160.888671875, "dur": 2142.89999008179, "ph": "X", "name": "ModifyCOMAndWindowsRuntimeTypes in assembly", "args": { "durationMS": 2.14289999008179, "detail": "Microsoft.MixedReality.Toolkit.SDK" } },
{ "pid": 1, "tid": 1, "ts": 724851.623535156, "dur": 46250.2021789551, "ph": "X", "name": "ApplyDefaultMarshalAsAttribute", "args": { "durationMS": 46.2502021789551, "detail": "" } },
{ "pid": 1, "tid": 1, "ts": 725083.374023438, "dur": 13462.4996185303, "ph": "X", "name": "ApplyDefaultMarshalAsAttributeVisitor in assembly", "args": { "durationMS": 13.4624996185303, "detail": "mscorlib" } },
{ "pid": 1, "tid": 1, "ts": 738575.1953125, "dur": 2797.30010032654, "ph": "X", "name": "ApplyDefaultMarshalAsAttributeVisitor in assembly", "args": { "durationMS": 2.79730010032654, "detail": "System" } },
{ "pid": 1, "tid": 1, "ts": 741634.826660156, "dur": 1938.40003013611, "ph": "X", "name": "ApplyDefaultMarshalAsAttributeVisitor in assembly", "args": { "durationMS": 1.93840003013611, "detail": "UnityEngine.CoreModule" } },
{ "pid": 1, "tid": 1, "ts": 745374.938964844, "dur": 1207.00001716614, "ph": "X", "name": "ApplyDefaultMarshalAsAttributeVisitor in assembly", "args": { "durationMS": 1.20700001716614, "detail": "UnityEngine.UI" } },
{ "pid": 1, "tid": 1, "ts": 746665.771484375, "dur": 5569.3998336792, "ph": "X", "name": "ApplyDefaultMarshalAsAttributeVisitor in assembly", "args": { "durationMS": 5.5693998336792, "detail": "UnityEngine.VRModule" } },
{ "pid": 1, "tid": 1, "ts": 752245.910644531, "dur": 1995.49996852875, "ph": "X", "name": "ApplyDefaultMarshalAsAttributeVisitor in assembly", "args": { "durationMS": 1.99549996852875, "detail": "Microsoft.MixedReality.Toolkit" } },
{ "pid": 1, "tid": 1, "ts": 754449.401855469, "dur": 348.800003528595, "ph": "X", "name": "ApplyDefaultMarshalAsAttributeVisitor in assembly", "args": { "durationMS": 0.348800003528595, "detail": "Microsoft.MixedReality.Toolkit.Services.InputSystem" } },
{ "pid": 1, "tid": 1, "ts": 754798.583984375, "dur": 1159.19995307922, "ph": "X", "name": "ApplyDefaultMarshalAsAttributeVisitor in assembly", "args": { "durationMS": 1.15919995307922, "detail": "Unity.TextMeshPro" } },
{ "pid": 1, "tid": 1, "ts": 756272.705078125, "dur": 1609.69996452332, "ph": "X", "name": "ApplyDefaultMarshalAsAttributeVisitor in assembly", "args": { "durationMS": 1.60969996452332, "detail": "Microsoft.MixedReality.Toolkit.SDK" } },
{ "pid": 1, "tid": 1, "ts": 757892.517089844, "dur": 347.900003194809, "ph": "X", "name": "ApplyDefaultMarshalAsAttributeVisitor in assembly", "args": { "durationMS": 0.347900003194809, "detail": "UnityEngine.AndroidJNIModule" } },
{ "pid": 1, "tid": 1, "ts": 758940.795898438, "dur": 9543.70021820068, "ph": "X", "name": "ApplyDefaultMarshalAsAttributeVisitor in assembly", "args": { "durationMS": 9.54370021820068, "detail": "I18N.Other" } },
{ "pid": 1, "tid": 1, "ts": 768811.645507813, "dur": 606.700003147125, "ph": "X", "name": "ApplyDefaultMarshalAsAttributeVisitor in assembly", "args": { "durationMS": 0.606700003147125, "detail": "Microsoft.MixedReality.Toolkit.Examples" } },
{ "pid": 1, "tid": 1, "ts": 770057.678222656, "dur": 938.099980354309, "ph": "X", "name": "ApplyDefaultMarshalAsAttributeVisitor in assembly", "args": { "durationMS": 0.938099980354309, "detail": "com.unity.multiplayer-hlapi.Runtime" } },
{ "pid": 1, "tid": 1, "ts": 771284.484863281, "dur": 6305.39989471436, "ph": "X", "name": "WriteResources", "args": { "durationMS": 6.30539989471436, "detail": "" } },
{ "pid": 1, "tid": 1, "ts": 777864.990234375, "dur": 32251.6975402832, "ph": "X", "name": "CopyEtcFolder", "args": { "durationMS": 32.2516975402832, "detail": "" } },
{ "pid": 1, "tid": 1, "ts": 810458.129882813, "dur": 383935.424804688, "ph": "X", "name": "PreProcessStage", "args": { "durationMS": 383.935424804688, "detail": "" } },
{ "pid": 1, "tid": 1, "ts": 1194397.33886719, "dur": 2128.59988212585, "ph": "X", "name": "Debugger Sequence Points", "args": { "durationMS": 2.12859988212585, "detail": "" } },
{ "pid": 1, "tid": 1, "ts": 1197113.89160156, "dur": 4679994.62890625, "ph": "X", "name": "Generics Collection", "args": { "durationMS": 4679.99462890625, "detail": "" } },
{ "pid": 1, "tid": 1, "ts": 1197114.01367188, "dur": 4643208.984375, "ph": "X", "name": "GenericsCollector.Collect", "args": { "durationMS": 4643.208984375, "detail": "" } },
{ "pid": 1, "tid": 1, "ts": 5840323.73046875, "dur": 35528.1982421875, "ph": "X", "name": "CollectGenericVirtualMethods.Collect", "args": { "durationMS": 35.5281982421875, "detail": "" } },
{ "pid": 1, "tid": 1, "ts": 5875852.05078125, "dur": 1025.79998970032, "ph": "X", "name": "AddExtraTypes", "args": { "durationMS": 1.02579998970032, "detail": "" } },
{ "pid": 1, "tid": 1, "ts": 5877108.3984375, "dur": 10754.0998458862, "ph": "X", "name": "Add Windows Runtime type names", "args": { "durationMS": 10.7540998458862, "detail": "" } },
{ "pid": 1, "tid": 1, "ts": 5877108.3984375, "dur": 10753.6001205444, "ph": "X", "name": "Add Windows Runtime type names", "args": { "durationMS": 10.7536001205444, "detail": "" } },
{ "pid": 1, "tid": 1, "ts": 5894688.96484375, "dur": 7921187.01171875, "ph": "X", "name": "AllAssemblyConversion", "args": { "durationMS": 7921.18701171875, "detail": "" } },
{ "pid": 1, "tid": 1, "ts": 5901965.8203125, "dur": 2229322.265625, "ph": "X", "name": "Convert", "args": { "durationMS": 2229.322265625, "detail": "mscorlib" } },
{ "pid": 1, "tid": 1, "ts": 5901966.796875, "dur": 2229320.80078125, "ph": "X", "name": "Code", "args": { "durationMS": 2229.32080078125, "detail": "" } },
{ "pid": 1, "tid": 1, "ts": 5902741.69921875, "dur": 2228545.41015625, "ph": "X", "name": "Methods", "args": { "durationMS": 2228.54541015625, "detail": "Definitions" } },
{ "pid": 1, "tid": 1, "ts": 8137194.82421875, "dur": 1047.99997806549, "ph": "X", "name": "Convert", "args": { "durationMS": 1.04799997806549, "detail": "System.Xml" } },
{ "pid": 1, "tid": 1, "ts": 8137197.265625, "dur": 1045.89998722076, "ph": "X", "name": "Code", "args": { "durationMS": 1.04589998722076, "detail": "" } },
{ "pid": 1, "tid": 1, "ts": 8137208.0078125, "dur": 1034.60001945496, "ph": "X", "name": "Methods", "args": { "durationMS": 1.03460001945496, "detail": "Definitions" } },
{ "pid": 1, "tid": 1, "ts": 8144320.3125, "dur": 7413.19990158081, "ph": "X", "name": "Convert", "args": { "durationMS": 7.41319990158081, "detail": "Mono.Security" } },
{ "pid": 1, "tid": 1, "ts": 8144323.2421875, "dur": 7410.29977798462, "ph": "X", "name": "Code", "args": { "durationMS": 7.41029977798462, "detail": "" } },
{ "pid": 1, "tid": 1, "ts": 8144328.125, "dur": 7405.00020980835, "ph": "X", "name": "Methods", "args": { "durationMS": 7.40500020980835, "detail": "Definitions" } },
{ "pid": 1, "tid": 1, "ts": 8157883.7890625, "dur": 286168.701171875, "ph": "X", "name": "Convert", "args": { "durationMS": 286.168701171875, "detail": "System" } },
{ "pid": 1, "tid": 1, "ts": 8157884.27734375, "dur": 286166.9921875, "ph": "X", "name": "Code", "args": { "durationMS": 286.1669921875, "detail": "" } },
{ "pid": 1, "tid": 1, "ts": 8157921.875, "dur": 286128.509521484, "ph": "X", "name": "Methods", "args": { "durationMS": 286.128509521484, "detail": "Definitions" } },
{ "pid": 1, "tid": 1, "ts": 8450245.1171875, "dur": 2389.89996910095, "ph": "X", "name": "Convert", "args": { "durationMS": 2.38989996910095, "detail": "System.Configuration" } },
{ "pid": 1, "tid": 1, "ts": 8450247.0703125, "dur": 2388.20004463196, "ph": "X", "name": "Code", "args": { "durationMS": 2.38820004463196, "detail": "" } },
{ "pid": 1, "tid": 1, "ts": 8450254.8828125, "dur": 2381.50000572205, "ph": "X", "name": "Methods", "args": { "durationMS": 2.38150000572205, "detail": "Definitions" } },
{ "pid": 1, "tid": 1, "ts": 8458708.0078125, "dur": 1493.29996109009, "ph": "X", "name": "Convert", "args": { "durationMS": 1.49329996109009, "detail": "System.Core" } },
{ "pid": 1, "tid": 1, "ts": 8458708.984375, "dur": 1492.10000038147, "ph": "X", "name": "Code", "args": { "durationMS": 1.49210000038147, "detail": "" } },
{ "pid": 1, "tid": 1, "ts": 8458715.8203125, "dur": 1484.79998111725, "ph": "X", "name": "Methods", "args": { "durationMS": 1.48479998111725, "detail": "Definitions" } },
{ "pid": 1, "tid": 1, "ts": 8465905.2734375, "dur": 11329.8997879028, "ph": "X", "name": "Convert", "args": { "durationMS": 11.3298997879028, "detail": "UnityEngine.SharedInternalsModule" } },
{ "pid": 1, "tid": 1, "ts": 8465906.25, "dur": 11328.7000656128, "ph": "X", "name": "Code", "args": { "durationMS": 11.3287000656128, "detail": "" } },
{ "pid": 1, "tid": 1, "ts": 8465915.0390625, "dur": 11319.8003768921, "ph": "X", "name": "Methods", "args": { "durationMS": 11.3198003768921, "detail": "Definitions" } },
{ "pid": 1, "tid": 1, "ts": 8483292.96875, "dur": 304310.089111328, "ph": "X", "name": "Convert", "args": { "durationMS": 304.310089111328, "detail": "UnityEngine.CoreModule" } },
{ "pid": 1, "tid": 1, "ts": 8483293.9453125, "dur": 304307.983398438, "ph": "X", "name": "Code", "args": { "durationMS": 304.307983398438, "detail": "" } },
{ "pid": 1, "tid": 1, "ts": 8483437.5, "dur": 304164.398193359, "ph": "X", "name": "Methods", "args": { "durationMS": 304.164398193359, "detail": "Definitions" } },
{ "pid": 1, "tid": 1, "ts": 8793115.234375, "dur": 11989.800453186, "ph": "X", "name": "Convert", "args": { "durationMS": 11.989800453186, "detail": "System.Numerics" } },
{ "pid": 1, "tid": 1, "ts": 8793116.2109375, "dur": 11988.2001876831, "ph": "X", "name": "Code", "args": { "durationMS": 11.9882001876831, "detail": "" } },
{ "pid": 1, "tid": 1, "ts": 8793122.0703125, "dur": 11983.4003448486, "ph": "X", "name": "Methods", "args": { "durationMS": 11.9834003448486, "detail": "Definitions" } },
{ "pid": 1, "tid": 1, "ts": 8810875, "dur": 19607.5992584229, "ph": "X", "name": "Convert", "args": { "durationMS": 19.6075992584229, "detail": "UnityEngine.PhysicsModule" } },
{ "pid": 1, "tid": 1, "ts": 8810876.953125, "dur": 19606.1000823975, "ph": "X", "name": "Code", "args": { "durationMS": 19.6061000823975, "detail": "" } },
{ "pid": 1, "tid": 1, "ts": 8810883.7890625, "dur": 19599.100112915, "ph": "X", "name": "Methods", "args": { "durationMS": 19.599100112915, "detail": "Definitions" } },
{ "pid": 1, "tid": 1, "ts": 8836210.9375, "dur": 12479.100227356, "ph": "X", "name": "Convert", "args": { "durationMS": 12.479100227356, "detail": "UnityEngine.TextRenderingModule" } },
{ "pid": 1, "tid": 1, "ts": 8836211.9140625, "dur": 12477.6000976563, "ph": "X", "name": "Code", "args": { "durationMS": 12.4776000976563, "detail": "" } },
{ "pid": 1, "tid": 1, "ts": 8836218.75, "dur": 12470.1995849609, "ph": "X", "name": "Methods", "args": { "durationMS": 12.4701995849609, "detail": "Definitions" } },
{ "pid": 1, "tid": 1, "ts": 8854396.484375, "dur": 561.500012874603, "ph": "X", "name": "Convert", "args": { "durationMS": 0.561500012874603, "detail": "System.Numerics.Vectors" } },
{ "pid": 1, "tid": 1, "ts": 8854397.4609375, "dur": 560.100018978119, "ph": "X", "name": "Code", "args": { "durationMS": 0.560100018978119, "detail": "" } },
{ "pid": 1, "tid": 1, "ts": 8854400.390625, "dur": 557.399988174438, "ph": "X", "name": "Methods", "args": { "durationMS": 0.557399988174438, "detail": "Definitions" } },
{ "pid": 1, "tid": 1, "ts": 8860569.3359375, "dur": 637.30001449585, "ph": "X", "name": "Convert", "args": { "durationMS": 0.63730001449585, "detail": "System.ObjectModel" } },
{ "pid": 1, "tid": 1, "ts": 8860571.2890625, "dur": 635.999977588654, "ph": "X", "name": "Code", "args": { "durationMS": 0.635999977588654, "detail": "" } },
{ "pid": 1, "tid": 1, "ts": 8860573.2421875, "dur": 632.89999961853, "ph": "X", "name": "Methods", "args": { "durationMS": 0.63289999961853, "detail": "Definitions" } },
{ "pid": 1, "tid": 1, "ts": 8867591.796875, "dur": 501.200020313263, "ph": "X", "name": "Convert", "args": { "durationMS": 0.501200020313263, "detail": "System.Runtime" } },
{ "pid": 1, "tid": 1, "ts": 8867593.75, "dur": 499.799996614456, "ph": "X", "name": "Code", "args": { "durationMS": 0.499799996614456, "detail": "" } },
{ "pid": 1, "tid": 1, "ts": 8867594.7265625, "dur": 497.299998998642, "ph": "X", "name": "Methods", "args": { "durationMS": 0.497299998998642, "detail": "Definitions" } },
{ "pid": 1, "tid": 1, "ts": 8873805.6640625, "dur": 567.900002002716, "ph": "X", "name": "Convert", "args": { "durationMS": 0.567900002002716, "detail": "System.Runtime.InteropServices.WindowsRuntime" } },
{ "pid": 1, "tid": 1, "ts": 8873806.640625, "dur": 566.200017929077, "ph": "X", "name": "Code", "args": { "durationMS": 0.566200017929077, "detail": "" } },
{ "pid": 1, "tid": 1, "ts": 8873809.5703125, "dur": 564.000010490417, "ph": "X", "name": "Methods", "args": { "durationMS": 0.564000010490417, "detail": "Definitions" } },
{ "pid": 1, "tid": 1, "ts": 8880013.671875, "dur": 1473.79994392395, "ph": "X", "name": "Convert", "args": { "durationMS": 1.47379994392395, "detail": "System.Runtime.WindowsRuntime.UI.Xaml" } },
{ "pid": 1, "tid": 1, "ts": 8880014.6484375, "dur": 1472.69999980927, "ph": "X", "name": "Code", "args": { "durationMS": 1.47269999980927, "detail": "" } },
{ "pid": 1, "tid": 1, "ts": 8880017.578125, "dur": 1470.00002861023, "ph": "X", "name": "Methods", "args": { "durationMS": 1.47000002861023, "detail": "Definitions" } },
{ "pid": 1, "tid": 1, "ts": 8887217.7734375, "dur": 45312.9005432129, "ph": "X", "name": "Convert", "args": { "durationMS": 45.3129005432129, "detail": "System.Runtime.WindowsRuntime" } },
{ "pid": 1, "tid": 1, "ts": 8887218.75, "dur": 45311.5997314453, "ph": "X", "name": "Code", "args": { "durationMS": 45.3115997314453, "detail": "" } },
{ "pid": 1, "tid": 1, "ts": 8887231.4453125, "dur": 45299.6978759766, "ph": "X", "name": "Methods", "args": { "durationMS": 45.2996978759766, "detail": "Definitions" } },
{ "pid": 1, "tid": 1, "ts": 8939068.359375, "dur": 18017.0001983643, "ph": "X", "name": "Convert", "args": { "durationMS": 18.0170001983643, "detail": "UnityEngine.AnimationModule" } },
{ "pid": 1, "tid": 1, "ts": 8939070.3125, "dur": 18015.3999328613, "ph": "X", "name": "Code", "args": { "durationMS": 18.0153999328613, "detail": "" } },
{ "pid": 1, "tid": 1, "ts": 8939081.0546875, "dur": 18004.8999786377, "ph": "X", "name": "Methods", "args": { "durationMS": 18.0048999786377, "detail": "Definitions" } },
{ "pid": 1, "tid": 1, "ts": 8963240.234375, "dur": 3340.10004997253, "ph": "X", "name": "Convert", "args": { "durationMS": 3.34010004997253, "detail": "UnityEngine.AssetBundleModule" } },
{ "pid": 1, "tid": 1, "ts": 8963242.1875, "dur": 3337.50009536743, "ph": "X", "name": "Code", "args": { "durationMS": 3.33750009536743, "detail": "" } },
{ "pid": 1, "tid": 1, "ts": 8963247.0703125, "dur": 3332.79991149902, "ph": "X", "name": "Methods", "args": { "durationMS": 3.33279991149902, "detail": "Definitions" } },
{ "pid": 1, "tid": 1, "ts": 8972498.046875, "dur": 89283.203125, "ph": "X", "name": "Convert", "args": { "durationMS": 89.283203125, "detail": "UnityEngine.IMGUIModule" } },
{ "pid": 1, "tid": 1, "ts": 8972500, "dur": 89281.2957763672, "ph": "X", "name": "Code", "args": { "durationMS": 89.2812957763672, "detail": "" } },
{ "pid": 1, "tid": 1, "ts": 8972509.765625, "dur": 89270.7977294922, "ph": "X", "name": "Methods", "args": { "durationMS": 89.2707977294922, "detail": "Definitions" } },
{ "pid": 1, "tid": 1, "ts": 9067582.03125, "dur": 9052.49977111816, "ph": "X", "name": "Convert", "args": { "durationMS": 9.05249977111816, "detail": "UnityEngine.InputLegacyModule" } },
{ "pid": 1, "tid": 1, "ts": 9067583.984375, "dur": 9050.70018768311, "ph": "X", "name": "Code", "args": { "durationMS": 9.05070018768311, "detail": "" } },
{ "pid": 1, "tid": 1, "ts": 9067588.8671875, "dur": 9045.80020904541, "ph": "X", "name": "Methods", "args": { "durationMS": 9.04580020904541, "detail": "Definitions" } },
{ "pid": 1, "tid": 1, "ts": 9082416.015625, "dur": 12483.5996627808, "ph": "X", "name": "Convert", "args": { "durationMS": 12.4835996627808, "detail": "UnityEngine.Physics2DModule" } },
{ "pid": 1, "tid": 1, "ts": 9082416.9921875, "dur": 12482.0003509521, "ph": "X", "name": "Code", "args": { "durationMS": 12.4820003509521, "detail": "" } },
{ "pid": 1, "tid": 1, "ts": 9082420.8984375, "dur": 12477.6000976563, "ph": "X", "name": "Methods", "args": { "durationMS": 12.4776000976563, "detail": "Definitions" } },
{ "pid": 1, "tid": 1, "ts": 9100753.90625, "dur": 10699.0003585815, "ph": "X", "name": "Convert", "args": { "durationMS": 10.6990003585815, "detail": "UnityEngine.UIModule" } },
{ "pid": 1, "tid": 1, "ts": 9100755.859375, "dur": 10697.2999572754, "ph": "X", "name": "Code", "args": { "durationMS": 10.6972999572754, "detail": "" } },
{ "pid": 1, "tid": 1, "ts": 9100760.7421875, "dur": 10691.6999816895, "ph": "X", "name": "Methods", "args": { "durationMS": 10.6916999816895, "detail": "Definitions" } },
{ "pid": 1, "tid": 1, "ts": 9117750.9765625, "dur": 33194.7021484375, "ph": "X", "name": "Convert", "args": { "durationMS": 33.1947021484375, "detail": "UnityEngine.XRModule" } },
{ "pid": 1, "tid": 1, "ts": 9117752.9296875, "dur": 33193.0999755859, "ph": "X", "name": "Code", "args": { "durationMS": 33.1930999755859, "detail": "" } },
{ "pid": 1, "tid": 1, "ts": 9117771.484375, "dur": 33174.5986938477, "ph": "X", "name": "Methods", "args": { "durationMS": 33.1745986938477, "detail": "Definitions" } },
{ "pid": 1, "tid": 1, "ts": 9157241.2109375, "dur": 15707.799911499, "ph": "X", "name": "Convert", "args": { "durationMS": 15.707799911499, "detail": "Microsoft.MixedReality.Toolkit.Async" } },
{ "pid": 1, "tid": 1, "ts": 9157243.1640625, "dur": 15705.8000564575, "ph": "X", "name": "Code", "args": { "durationMS": 15.7058000564575, "detail": "" } },
{ "pid": 1, "tid": 1, "ts": 9157251.953125, "dur": 15697.2990036011, "ph": "X", "name": "Methods", "args": { "durationMS": 15.6972990036011, "detail": "Definitions" } },
{ "pid": 1, "tid": 1, "ts": 9179169.921875, "dur": 8473.09970855713, "ph": "X", "name": "Convert", "args": { "durationMS": 8.47309970855713, "detail": "UnityEngine.AudioModule" } },
{ "pid": 1, "tid": 1, "ts": 9179171.875, "dur": 8471.59957885742, "ph": "X", "name": "Code", "args": { "durationMS": 8.47159957885742, "detail": "" } },
{ "pid": 1, "tid": 1, "ts": 9179177.734375, "dur": 8465.20042419434, "ph": "X", "name": "Methods", "args": { "durationMS": 8.46520042419434, "detail": "Definitions" } },
{ "pid": 1, "tid": 1, "ts": 9193753.90625, "dur": 4134.39989089966, "ph": "X", "name": "Convert", "args": { "durationMS": 4.13439989089966, "detail": "UnityEngine.JSONSerializeModule" } },
{ "pid": 1, "tid": 1, "ts": 9193755.859375, "dur": 4132.99989700317, "ph": "X", "name": "Code", "args": { "durationMS": 4.13299989700317, "detail": "" } },
{ "pid": 1, "tid": 1, "ts": 9193757.8125, "dur": 4130.30004501343, "ph": "X", "name": "Methods", "args": { "durationMS": 4.13030004501343, "detail": "Definitions" } },
{ "pid": 1, "tid": 1, "ts": 9203738.28125, "dur": 11080.3003311157, "ph": "X", "name": "Convert", "args": { "durationMS": 11.0803003311157, "detail": "UnityEngine.ParticleSystemModule" } },
{ "pid": 1, "tid": 1, "ts": 9203740.234375, "dur": 11079.0996551514, "ph": "X", "name": "Code", "args": { "durationMS": 11.0790996551514, "detail": "" } },
{ "pid": 1, "tid": 1, "ts": 9203745.1171875, "dur": 11073.6999511719, "ph": "X", "name": "Methods", "args": { "durationMS": 11.0736999511719, "detail": "Definitions" } },
{ "pid": 1, "tid": 1, "ts": 9220714.84375, "dur": 472411.499023438, "ph": "X", "name": "Convert", "args": { "durationMS": 472.411499023438, "detail": "UnityEngine.UI" } },
{ "pid": 1, "tid": 1, "ts": 9220716.796875, "dur": 472409.912109375, "ph": "X", "name": "Code", "args": { "durationMS": 472.409912109375, "detail": "" } },
{ "pid": 1, "tid": 1, "ts": 9220761.71875, "dur": 472364.288330078, "ph": "X", "name": "Methods", "args": { "durationMS": 472.364288330078, "detail": "Definitions" } },
{ "pid": 1, "tid": 1, "ts": 9698758.7890625, "dur": 30854.4998168945, "ph": "X", "name": "Convert", "args": { "durationMS": 30.8544998168945, "detail": "UnityEngine.UnityWebRequestModule" } },
{ "pid": 1, "tid": 1, "ts": 9698760.7421875, "dur": 30852.6020050049, "ph": "X", "name": "Code", "args": { "durationMS": 30.8526020050049, "detail": "" } },
{ "pid": 1, "tid": 1, "ts": 9698765.625, "dur": 30846.5976715088, "ph": "X", "name": "Methods", "args": { "durationMS": 30.8465976715088, "detail": "Definitions" } },
{ "pid": 1, "tid": 1, "ts": 9736218.75, "dur": 53370.2011108398, "ph": "X", "name": "Convert", "args": { "durationMS": 53.3702011108398, "detail": "UnityEngine.VRModule" } },
{ "pid": 1, "tid": 1, "ts": 9736221.6796875, "dur": 53367.9008483887, "ph": "X", "name": "Code", "args": { "durationMS": 53.3679008483887, "detail": "" } },
{ "pid": 1, "tid": 1, "ts": 9736240.234375, "dur": 53349.1020202637, "ph": "X", "name": "Methods", "args": { "durationMS": 53.3491020202637, "detail": "Definitions" } },
{ "pid": 1, "tid": 1, "ts": 9795530.2734375, "dur": 74348.0987548828, "ph": "X", "name": "Convert", "args": { "durationMS": 74.3480987548828, "detail": "WindowsRuntimeMetadata" } },
{ "pid": 1, "tid": 1, "ts": 9795531.25, "dur": 74347.0001220703, "ph": "X", "name": "Code", "args": { "durationMS": 74.3470001220703, "detail": "" } },
{ "pid": 1, "tid": 1, "ts": 9795579.1015625, "dur": 74298.698425293, "ph": "X", "name": "Methods", "args": { "durationMS": 74.298698425293, "detail": "Definitions" } },
{ "pid": 1, "tid": 1, "ts": 9876461.9140625, "dur": 663249.694824219, "ph": "X", "name": "Convert", "args": { "durationMS": 663.249694824219, "detail": "Microsoft.MixedReality.Toolkit" } },
{ "pid": 1, "tid": 1, "ts": 9876462.890625, "dur": 663248.046875, "ph": "X", "name": "Code", "args": { "durationMS": 663.248046875, "detail": "" } },
{ "pid": 1, "tid": 1, "ts": 9876558.59375, "dur": 663152.160644531, "ph": "X", "name": "Methods", "args": { "durationMS": 663.152160644531, "detail": "Definitions" } },
{ "pid": 1, "tid": 1, "ts": 10550921.875, "dur": 27020.7996368408, "ph": "X", "name": "Convert", "args": { "durationMS": 27.0207996368408, "detail": "UnityEngine.TextCoreModule" } },
{ "pid": 1, "tid": 1, "ts": 10550923.828125, "dur": 27017.9004669189, "ph": "X", "name": "Code", "args": { "durationMS": 27.0179004669189, "detail": "" } },
{ "pid": 1, "tid": 1, "ts": 10550932.6171875, "dur": 27009.0999603271, "ph": "X", "name": "Methods", "args": { "durationMS": 27.0090999603271, "detail": "Definitions" } },
{ "pid": 1, "tid": 1, "ts": 10583585.9375, "dur": 34742.2027587891, "ph": "X", "name": "Convert", "args": { "durationMS": 34.7422027587891, "detail": "Microsoft.MixedReality.Toolkit.Services.InputAnimation" } },
{ "pid": 1, "tid": 1, "ts": 10583587.890625, "dur": 34740.4975891113, "ph": "X", "name": "Code", "args": { "durationMS": 34.7404975891113, "detail": "" } },
{ "pid": 1, "tid": 1, "ts": 10583594.7265625, "dur": 34733.4022521973, "ph": "X", "name": "Methods", "args": { "durationMS": 34.7334022521973, "detail": "Definitions" } },
{ "pid": 1, "tid": 1, "ts": 10624200.1953125, "dur": 132283.706665039, "ph": "X", "name": "Convert", "args": { "durationMS": 132.283706665039, "detail": "Microsoft.MixedReality.Toolkit.Services.InputSystem" } },
{ "pid": 1, "tid": 1, "ts": 10624201.171875, "dur": 132281.799316406, "ph": "X", "name": "Code", "args": { "durationMS": 132.281799316406, "detail": "" } },
{ "pid": 1, "tid": 1, "ts": 10624210.9375, "dur": 132272.903442383, "ph": "X", "name": "Methods", "args": { "durationMS": 132.272903442383, "detail": "Definitions" } },
{ "pid": 1, "tid": 1, "ts": 10762531.25, "dur": 687084.47265625, "ph": "X", "name": "Convert", "args": { "durationMS": 687.08447265625, "detail": "Unity.TextMeshPro" } },
{ "pid": 1, "tid": 1, "ts": 10762531.25, "dur": 687082.885742188, "ph": "X", "name": "Code", "args": { "durationMS": 687.082885742188, "detail": "" } },
{ "pid": 1, "tid": 1, "ts": 10762567.3828125, "dur": 687046.38671875, "ph": "X", "name": "Methods", "args": { "durationMS": 687.04638671875, "detail": "Definitions" } },
{ "pid": 1, "tid": 1, "ts": 11458331.0546875, "dur": 929.400026798248, "ph": "X", "name": "Convert", "args": { "durationMS": 0.929400026798248, "detail": "UnityEngine.GridModule" } },
{ "pid": 1, "tid": 1, "ts": 11458333.0078125, "dur": 926.599979400635, "ph": "X", "name": "Code", "args": { "durationMS": 0.926599979400635, "detail": "" } },
{ "pid": 1, "tid": 1, "ts": 11458339.84375, "dur": 919.200003147125, "ph": "X", "name": "Methods", "args": { "durationMS": 0.919200003147125, "detail": "Definitions" } },
{ "pid": 1, "tid": 1, "ts": 11467604.4921875, "dur": 5224.10011291504, "ph": "X", "name": "Convert", "args": { "durationMS": 5.22410011291504, "detail": "UnityEngine.ImageConversionModule" } },
{ "pid": 1, "tid": 1, "ts": 11467607.421875, "dur": 5221.49991989136, "ph": "X", "name": "Code", "args": { "durationMS": 5.22149991989136, "detail": "" } },
{ "pid": 1, "tid": 1, "ts": 11467611.328125, "dur": 5217.10014343262, "ph": "X", "name": "Methods", "args": { "durationMS": 5.21710014343262, "detail": "Definitions" } },
{ "pid": 1, "tid": 1, "ts": 11481162.109375, "dur": 52957.7980041504, "ph": "X", "name": "Convert", "args": { "durationMS": 52.9577980041504, "detail": "I18N" } },
{ "pid": 1, "tid": 1, "ts": 11481164.0625, "dur": 52955.5015563965, "ph": "X", "name": "Code", "args": { "durationMS": 52.9555015563965, "detail": "" } },
{ "pid": 1, "tid": 1, "ts": 11481171.875, "dur": 52948.1010437012, "ph": "X", "name": "Methods", "args": { "durationMS": 52.9481010437012, "detail": "Definitions" } },
{ "pid": 1, "tid": 1, "ts": 11539832.03125, "dur": 73688.4002685547, "ph": "X", "name": "Convert", "args": { "durationMS": 73.6884002685547, "detail": "Microsoft.MixedReality.Toolkit.Gltf" } },
{ "pid": 1, "tid": 1, "ts": 11539833.984375, "dur": 73686.7980957031, "ph": "X", "name": "Code", "args": { "durationMS": 73.6867980957031, "detail": "" } },
{ "pid": 1, "tid": 1, "ts": 11539848.6328125, "dur": 73671.6995239258, "ph": "X", "name": "Methods", "args": { "durationMS": 73.6716995239258, "detail": "Definitions" } },
{ "pid": 1, "tid": 1, "ts": 11619350.5859375, "dur": 621419.189453125, "ph": "X", "name": "Convert", "args": { "durationMS": 621.419189453125, "detail": "Microsoft.MixedReality.Toolkit.SDK" } },
{ "pid": 1, "tid": 1, "ts": 11619352.5390625, "dur": 621417.541503906, "ph": "X", "name": "Code", "args": { "durationMS": 621.417541503906, "detail": "" } },
{ "pid": 1, "tid": 1, "ts": 11619434.5703125, "dur": 621335.815429688, "ph": "X", "name": "Methods", "args": { "durationMS": 621.335815429688, "detail": "Definitions" } },
{ "pid": 1, "tid": 1, "ts": 12246798.828125, "dur": 1289.49999809265, "ph": "X", "name": "Convert", "args": { "durationMS": 1.28949999809265, "detail": "UnityEngine.AIModule" } },
{ "pid": 1, "tid": 1, "ts": 12246800.78125, "dur": 1287.8999710083, "ph": "X", "name": "Code", "args": { "durationMS": 1.2878999710083, "detail": "" } },
{ "pid": 1, "tid": 1, "ts": 12246803.7109375, "dur": 1284.29996967316, "ph": "X", "name": "Methods", "args": { "durationMS": 1.28429996967316, "detail": "Definitions" } },
{ "pid": 1, "tid": 1, "ts": 12253636.71875, "dur": 36431.4994812012, "ph": "X", "name": "Convert", "args": { "durationMS": 36.4314994812012, "detail": "UnityEngine.AndroidJNIModule" } },
{ "pid": 1, "tid": 1, "ts": 12253638.671875, "dur": 36430.3016662598, "ph": "X", "name": "Code", "args": { "durationMS": 36.4303016662598, "detail": "" } },
{ "pid": 1, "tid": 1, "ts": 12253643.5546875, "dur": 36425.3005981445, "ph": "X", "name": "Methods", "args": { "durationMS": 36.4253005981445, "detail": "Definitions" } },
{ "pid": 1, "tid": 1, "ts": 12295711.9140625, "dur": 1317.70002841949, "ph": "X", "name": "Convert", "args": { "durationMS": 1.31770002841949, "detail": "UnityEngine.DirectorModule" } },
{ "pid": 1, "tid": 1, "ts": 12295713.8671875, "dur": 1315.99998474121, "ph": "X", "name": "Code", "args": { "durationMS": 1.31599998474121, "detail": "" } },
{ "pid": 1, "tid": 1, "ts": 12295716.796875, "dur": 1312.99996376038, "ph": "X", "name": "Methods", "args": { "durationMS": 1.31299996376038, "detail": "Definitions" } },
{ "pid": 1, "tid": 1, "ts": 12302703.125, "dur": 3485.50009727478, "ph": "X", "name": "Convert", "args": { "durationMS": 3.48550009727478, "detail": "UnityEngine.InputModule" } },
{ "pid": 1, "tid": 1, "ts": 12302704.1015625, "dur": 3484.20000076294, "ph": "X", "name": "Code", "args": { "durationMS": 3.48420000076294, "detail": "" } },
{ "pid": 1, "tid": 1, "ts": 12302707.03125, "dur": 3480.79991340637, "ph": "X", "name": "Methods", "args": { "durationMS": 3.48079991340637, "detail": "Definitions" } },
{ "pid": 1, "tid": 1, "ts": 12311927.734375, "dur": 14761.6996765137, "ph": "X", "name": "Convert", "args": { "durationMS": 14.7616996765137, "detail": "UnityEngine.TerrainModule" } },
{ "pid": 1, "tid": 1, "ts": 12311929.6875, "dur": 14760.0002288818, "ph": "X", "name": "Code", "args": { "durationMS": 14.7600002288818, "detail": "" } },
{ "pid": 1, "tid": 1, "ts": 12311936.5234375, "dur": 14753.5009384155, "ph": "X", "name": "Methods", "args": { "durationMS": 14.7535009384155, "detail": "Definitions" } },
{ "pid": 1, "tid": 1, "ts": 12332389.6484375, "dur": 5997.79987335205, "ph": "X", "name": "Convert", "args": { "durationMS": 5.99779987335205, "detail": "UnityEngine.TilemapModule" } },
{ "pid": 1, "tid": 1, "ts": 12332390.625, "dur": 5996.20008468628, "ph": "X", "name": "Code", "args": { "durationMS": 5.99620008468628, "detail": "" } },
{ "pid": 1, "tid": 1, "ts": 12332394.53125, "dur": 5991.19997024536, "ph": "X", "name": "Methods", "args": { "durationMS": 5.99119997024536, "detail": "Definitions" } },
{ "pid": 1, "tid": 1, "ts": 12344097.65625, "dur": 4164.99996185303, "ph": "X", "name": "Convert", "args": { "durationMS": 4.16499996185303, "detail": "UnityEngine.UIElementsModule" } },
{ "pid": 1, "tid": 1, "ts": 12344099.609375, "dur": 4163.09976577759, "ph": "X", "name": "Code", "args": { "durationMS": 4.16309976577759, "detail": "" } },
{ "pid": 1, "tid": 1, "ts": 12344103.515625, "dur": 4158.59985351563, "ph": "X", "name": "Methods", "args": { "durationMS": 4.15859985351563, "detail": "Definitions" } },
{ "pid": 1, "tid": 1, "ts": 12354040.0390625, "dur": 59602.4017333984, "ph": "X", "name": "Convert", "args": { "durationMS": 59.6024017333984, "detail": "UnityEngine.UNETModule" } },
{ "pid": 1, "tid": 1, "ts": 12354041.015625, "dur": 59601.203918457, "ph": "X", "name": "Code", "args": { "durationMS": 59.601203918457, "detail": "" } },
{ "pid": 1, "tid": 1, "ts": 12354057.6171875, "dur": 59584.300994873, "ph": "X", "name": "Methods", "args": { "durationMS": 59.584300994873, "detail": "Definitions" } },
{ "pid": 1, "tid": 1, "ts": 12419748.046875, "dur": 4081.60018920898, "ph": "X", "name": "Convert", "args": { "durationMS": 4.08160018920898, "detail": "UnityEngine.UnityAnalyticsModule" } },
{ "pid": 1, "tid": 1, "ts": 12419749.0234375, "dur": 4079.89978790283, "ph": "X", "name": "Code", "args": { "durationMS": 4.07989978790283, "detail": "" } },
{ "pid": 1, "tid": 1, "ts": 12419757.8125, "dur": 4071.30002975464, "ph": "X", "name": "Methods", "args": { "durationMS": 4.07130002975464, "detail": "Definitions" } },
{ "pid": 1, "tid": 1, "ts": 12429436.5234375, "dur": 3449.89991188049, "ph": "X", "name": "Convert", "args": { "durationMS": 3.44989991188049, "detail": "UnityEngine.VFXModule" } },
{ "pid": 1, "tid": 1, "ts": 12429438.4765625, "dur": 3448.60005378723, "ph": "X", "name": "Code", "args": { "durationMS": 3.44860005378723, "detail": "" } },
{ "pid": 1, "tid": 1, "ts": 12429443.359375, "dur": 3443.70007514954, "ph": "X", "name": "Methods", "args": { "durationMS": 3.44370007514954, "detail": "Definitions" } },
{ "pid": 1, "tid": 1, "ts": 12438589.84375, "dur": 4489.39990997314, "ph": "X", "name": "Convert", "args": { "durationMS": 4.48939990997314, "detail": "UnityEngine.VideoModule" } },
{ "pid": 1, "tid": 1, "ts": 12438591.796875, "dur": 4487.99991607666, "ph": "X", "name": "Code", "args": { "durationMS": 4.48799991607666, "detail": "" } },
{ "pid": 1, "tid": 1, "ts": 12438599.609375, "dur": 4480.70001602173, "ph": "X", "name": "Methods", "args": { "durationMS": 4.48070001602173, "detail": "Definitions" } },
{ "pid": 1, "tid": 1, "ts": 12449809.5703125, "dur": 42942.4018859863, "ph": "X", "name": "Convert", "args": { "durationMS": 42.9424018859863, "detail": "I18N.CJK" } },
{ "pid": 1, "tid": 1, "ts": 12449812.5, "dur": 42939.8994445801, "ph": "X", "name": "Code", "args": { "durationMS": 42.9398994445801, "detail": "" } },
{ "pid": 1, "tid": 1, "ts": 12449831.0546875, "dur": 42921.6003417969, "ph": "X", "name": "Methods", "args": { "durationMS": 42.9216003417969, "detail": "Definitions" } },
{ "pid": 1, "tid": 1, "ts": 12498649.4140625, "dur": 17556.4994812012, "ph": "X", "name": "Convert", "args": { "durationMS": 17.5564994812012, "detail": "I18N.MidEast" } },
{ "pid": 1, "tid": 1, "ts": 12498650.390625, "dur": 17554.8992156982, "ph": "X", "name": "Code", "args": { "durationMS": 17.5548992156982, "detail": "" } },
{ "pid": 1, "tid": 1, "ts": 12498655.2734375, "dur": 17548.2006072998, "ph": "X", "name": "Methods", "args": { "durationMS": 17.5482006072998, "detail": "Definitions" } },
{ "pid": 1, "tid": 1, "ts": 12522143.5546875, "dur": 22184.2002868652, "ph": "X", "name": "Convert", "args": { "durationMS": 22.1842002868652, "detail": "I18N.Other" } },
{ "pid": 1, "tid": 1, "ts": 12522145.5078125, "dur": 22182.8994750977, "ph": "X", "name": "Code", "args": { "durationMS": 22.1828994750977, "detail": "" } },
{ "pid": 1, "tid": 1, "ts": 12522156.25, "dur": 22172.1000671387, "ph": "X", "name": "Methods", "args": { "durationMS": 22.1721000671387, "detail": "Definitions" } },
{ "pid": 1, "tid": 1, "ts": 12550671.875, "dur": 132919.708251953, "ph": "X", "name": "Convert", "args": { "durationMS": 132.919708251953, "detail": "I18N.Rare" } },
{ "pid": 1, "tid": 1, "ts": 12550672.8515625, "dur": 132917.694091797, "ph": "X", "name": "Code", "args": { "durationMS": 132.917694091797, "detail": "" } },
{ "pid": 1, "tid": 1, "ts": 12550698.2421875, "dur": 132891.6015625, "ph": "X", "name": "Methods", "args": { "durationMS": 132.8916015625, "detail": "Definitions" } },
{ "pid": 1, "tid": 1, "ts": 12689301.7578125, "dur": 46583.9004516602, "ph": "X", "name": "Convert", "args": { "durationMS": 46.5839004516602, "detail": "I18N.West" } },
{ "pid": 1, "tid": 1, "ts": 12689302.734375, "dur": 46582.4012756348, "ph": "X", "name": "Code", "args": { "durationMS": 46.5824012756348, "detail": "" } },
{ "pid": 1, "tid": 1, "ts": 12689313.4765625, "dur": 46572.0977783203, "ph": "X", "name": "Methods", "args": { "durationMS": 46.5720977783203, "detail": "Definitions" } },
{ "pid": 1, "tid": 1, "ts": 12741629.8828125, "dur": 7168.09988021851, "ph": "X", "name": "Convert", "args": { "durationMS": 7.16809988021851, "detail": "Microsoft.MixedReality.Toolkit.Demos.Gltf" } },
{ "pid": 1, "tid": 1, "ts": 12741630.859375, "dur": 7166.50009155273, "ph": "X", "name": "Code", "args": { "durationMS": 7.16650009155273, "detail": "" } },
{ "pid": 1, "tid": 1, "ts": 12741635.7421875, "dur": 7162.49990463257, "ph": "X", "name": "Methods", "args": { "durationMS": 7.16249990463257, "detail": "Definitions" } },
{ "pid": 1, "tid": 1, "ts": 12754766.6015625, "dur": 3215.69991111755, "ph": "X", "name": "Convert", "args": { "durationMS": 3.21569991111755, "detail": "Microsoft.MixedReality.Toolkit.Demos.InspectorFields" } },
{ "pid": 1, "tid": 1, "ts": 12754767.578125, "dur": 3214.40005302429, "ph": "X", "name": "Code", "args": { "durationMS": 3.21440005302429, "detail": "" } },
{ "pid": 1, "tid": 1, "ts": 12754770.5078125, "dur": 3211.60006523132, "ph": "X", "name": "Methods", "args": { "durationMS": 3.21160006523132, "detail": "Definitions" } },
{ "pid": 1, "tid": 1, "ts": 12764457.03125, "dur": 5509.90009307861, "ph": "X", "name": "Convert", "args": { "durationMS": 5.50990009307861, "detail": "Microsoft.MixedReality.Toolkit.Demos.UX.Interactables" } },
{ "pid": 1, "tid": 1, "ts": 12764459.9609375, "dur": 5506.8998336792, "ph": "X", "name": "Code", "args": { "durationMS": 5.5068998336792, "detail": "" } },
{ "pid": 1, "tid": 1, "ts": 12764463.8671875, "dur": 5502.29978561401, "ph": "X", "name": "Methods", "args": { "durationMS": 5.50229978561401, "detail": "Definitions" } },
{ "pid": 1, "tid": 1, "ts": 12775744.140625, "dur": 235871.688842773, "ph": "X", "name": "Convert", "args": { "durationMS": 235.871688842773, "detail": "Microsoft.MixedReality.Toolkit.Examples" } },
{ "pid": 1, "tid": 1, "ts": 12775746.09375, "dur": 235870.315551758, "ph": "X", "name": "Code", "args": { "durationMS": 235.870315551758, "detail": "" } },
{ "pid": 1, "tid": 1, "ts": 12775771.484375, "dur": 235844.711303711, "ph": "X", "name": "Methods", "args": { "durationMS": 235.844711303711, "detail": "Definitions" } },
{ "pid": 1, "tid": 1, "ts": 13017639.6484375, "dur": 92299.4003295898, "ph": "X", "name": "Convert", "args": { "durationMS": 92.2994003295898, "detail": "Microsoft.MixedReality.Toolkit.Providers.WindowsMixedReality" } },
{ "pid": 1, "tid": 1, "ts": 13017640.625, "dur": 92297.1038818359, "ph": "X", "name": "Code", "args": { "durationMS": 92.2971038818359, "detail": "" } },
{ "pid": 1, "tid": 1, "ts": 13017650.390625, "dur": 92288.4979248047, "ph": "X", "name": "Methods", "args": { "durationMS": 92.2884979248047, "detail": "Definitions" } },
{ "pid": 1, "tid": 1, "ts": 13115814.453125, "dur": 20695.2991485596, "ph": "X", "name": "Convert", "args": { "durationMS": 20.6952991485596, "detail": "Microsoft.MixedReality.Toolkit.Providers.WindowsVoiceInput" } },
{ "pid": 1, "tid": 1, "ts": 13115816.40625, "dur": 20693.2983398438, "ph": "X", "name": "Code", "args": { "durationMS": 20.6932983398438, "detail": "" } },
{ "pid": 1, "tid": 1, "ts": 13115820.3125, "dur": 20688.1999969482, "ph": "X", "name": "Methods", "args": { "durationMS": 20.6881999969482, "detail": "Definitions" } },
{ "pid": 1, "tid": 1, "ts": 13142829.1015625, "dur": 20651.2985229492, "ph": "X", "name": "Convert", "args": { "durationMS": 20.6512985229492, "detail": "Microsoft.MixedReality.Toolkit.Services.BoundarySystem" } },
{ "pid": 1, "tid": 1, "ts": 13142831.0546875, "dur": 20648.7998962402, "ph": "X", "name": "Code", "args": { "durationMS": 20.6487998962402, "detail": "" } },
{ "pid": 1, "tid": 1, "ts": 13142833.984375, "dur": 20644.8993682861, "ph": "X", "name": "Methods", "args": { "durationMS": 20.6448993682861, "detail": "Definitions" } },
{ "pid": 1, "tid": 1, "ts": 13169214.84375, "dur": 5310.69993972778, "ph": "X", "name": "Convert", "args": { "durationMS": 5.31069993972778, "detail": "Microsoft.MixedReality.Toolkit.Services.CameraSystem" } },
{ "pid": 1, "tid": 1, "ts": 13169216.796875, "dur": 5308.8002204895, "ph": "X", "name": "Code", "args": { "durationMS": 5.3088002204895, "detail": "" } },
{ "pid": 1, "tid": 1, "ts": 13169219.7265625, "dur": 5305.69982528687, "ph": "X", "name": "Methods", "args": { "durationMS": 5.30569982528687, "detail": "Definitions" } },
{ "pid": 1, "tid": 1, "ts": 13180377.9296875, "dur": 27860.4984283447, "ph": "X", "name": "Convert", "args": { "durationMS": 27.8604984283447, "detail": "Microsoft.MixedReality.Toolkit.Services.DiagnosticsSystem" } },
{ "pid": 1, "tid": 1, "ts": 13180379.8828125, "dur": 27858.8008880615, "ph": "X", "name": "Code", "args": { "durationMS": 27.8588008880615, "detail": "" } },
{ "pid": 1, "tid": 1, "ts": 13180384.765625, "dur": 27854.0000915527, "ph": "X", "name": "Methods", "args": { "durationMS": 27.8540000915527, "detail": "Definitions" } },
{ "pid": 1, "tid": 1, "ts": 13213845.703125, "dur": 40183.6013793945, "ph": "X", "name": "Convert", "args": { "durationMS": 40.1836013793945, "detail": "Microsoft.MixedReality.Toolkit.Services.InputSimulation" } },
{ "pid": 1, "tid": 1, "ts": 13213847.65625, "dur": 40181.999206543, "ph": "X", "name": "Code", "args": { "durationMS": 40.181999206543, "detail": "" } },
{ "pid": 1, "tid": 1, "ts": 13213854.4921875, "dur": 40174.5986938477, "ph": "X", "name": "Methods", "args": { "durationMS": 40.1745986938477, "detail": "Definitions" } },
{ "pid": 1, "tid": 1, "ts": 13259639.6484375, "dur": 40684.1011047363, "ph": "X", "name": "Convert", "args": { "durationMS": 40.6841011047363, "detail": "Microsoft.MixedReality.Toolkit.Services.SceneSystem" } },
{ "pid": 1, "tid": 1, "ts": 13259640.625, "dur": 40682.3997497559, "ph": "X", "name": "Code", "args": { "durationMS": 40.6823997497559, "detail": "" } },
{ "pid": 1, "tid": 1, "ts": 13259647.4609375, "dur": 40675.2014160156, "ph": "X", "name": "Methods", "args": { "durationMS": 40.6752014160156, "detail": "Definitions" } },
{ "pid": 1, "tid": 1, "ts": 13306303.7109375, "dur": 7085.00003814697, "ph": "X", "name": "Convert", "args": { "durationMS": 7.08500003814697, "detail": "Microsoft.MixedReality.Toolkit.Services.SpatialAwarenessSystem" } },
{ "pid": 1, "tid": 1, "ts": 13306305.6640625, "dur": 7083.19997787476, "ph": "X", "name": "Code", "args": { "durationMS": 7.08319997787476, "detail": "" } },
{ "pid": 1, "tid": 1, "ts": 13306308.59375, "dur": 7080.29985427856, "ph": "X", "name": "Methods", "args": { "durationMS": 7.08029985427856, "detail": "Definitions" } },
{ "pid": 1, "tid": 1, "ts": 13320091.796875, "dur": 6409.39998626709, "ph": "X", "name": "Convert", "args": { "durationMS": 6.40939998626709, "detail": "Microsoft.MixedReality.Toolkit.Services.TeleportSystem" } },
{ "pid": 1, "tid": 1, "ts": 13320094.7265625, "dur": 6407.19985961914, "ph": "X", "name": "Code", "args": { "durationMS": 6.40719985961914, "detail": "" } },
{ "pid": 1, "tid": 1, "ts": 13320096.6796875, "dur": 6404.09994125366, "ph": "X", "name": "Methods", "args": { "durationMS": 6.40409994125366, "detail": "Definitions" } },
{ "pid": 1, "tid": 1, "ts": 13332326.171875, "dur": 532.299995422363, "ph": "X", "name": "Convert", "args": { "durationMS": 0.532299995422363, "detail": "UnityEngine" } },
{ "pid": 1, "tid": 1, "ts": 13332327.1484375, "dur": 531.000018119812, "ph": "X", "name": "Code", "args": { "durationMS": 0.531000018119812, "detail": "" } },
{ "pid": 1, "tid": 1, "ts": 13332329.1015625, "dur": 528.500020503998, "ph": "X", "name": "Methods", "args": { "durationMS": 0.528500020503998, "detail": "Definitions" } },
{ "pid": 1, "tid": 1, "ts": 13338733.3984375, "dur": 434051.696777344, "ph": "X", "name": "Convert", "args": { "durationMS": 434.051696777344, "detail": "com.unity.multiplayer-hlapi.Runtime" } },
{ "pid": 1, "tid": 1, "ts": 13338734.375, "dur": 434050.415039063, "ph": "X", "name": "Code", "args": { "durationMS": 434.050415039063, "detail": "" } },
{ "pid": 1, "tid": 1, "ts": 13338760.7421875, "dur": 434023.468017578, "ph": "X", "name": "Methods", "args": { "durationMS": 434.023468017578, "detail": "Definitions" } },
{ "pid": 1, "tid": 1, "ts": 13778627.9296875, "dur": 37245.8000183105, "ph": "X", "name": "Convert", "args": { "durationMS": 37.2458000183105, "detail": "Assembly-CSharp" } },
{ "pid": 1, "tid": 1, "ts": 13778627.9296875, "dur": 37244.4000244141, "ph": "X", "name": "Code", "args": { "durationMS": 37.2444000244141, "detail": "" } },
{ "pid": 1, "tid": 1, "ts": 13778635.7421875, "dur": 37237.1025085449, "ph": "X", "name": "Methods", "args": { "durationMS": 37.2371025085449, "detail": "Definitions" } },
{ "pid": 1, "tid": 1, "ts": 13815876.953125, "dur": 9703334.9609375, "ph": "X", "name": "WriteGenerics", "args": { "durationMS": 9703.3349609375, "detail": "" } },
{ "pid": 1, "tid": 1, "ts": 13823385.7421875, "dur": 31631.9007873535, "ph": "X", "name": "Arrays Definitions", "args": { "durationMS": 31.6319007873535, "detail": "" } },
{ "pid": 1, "tid": 1, "ts": 13855323.2421875, "dur": 1221077.88085938, "ph": "X", "name": "GenericInstanceMethods", "args": { "durationMS": 1221.07788085938, "detail": "" } },
{ "pid": 1, "tid": 1, "ts": 15076401.3671875, "dur": 7339233.3984375, "ph": "X", "name": "GenericInstanceTypes", "args": { "durationMS": 7339.2333984375, "detail": "" } },
{ "pid": 1, "tid": 1, "ts": 22415824.21875, "dur": 1103363.89160156, "ph": "X", "name": "GenericComDefinitions", "args": { "durationMS": 1103.36389160156, "detail": "" } },
{ "pid": 1, "tid": 1, "ts": 23528345.703125, "dur": 340647.918701172, "ph": "X", "name": "MetadataCollector", "args": { "durationMS": 340.647918701172, "detail": "" } },
{ "pid": 1, "tid": 1, "ts": 23529880.859375, "dur": 12640.9997940063, "ph": "X", "name": "UpdateEmptyTokens", "args": { "durationMS": 12.6409997940063, "detail": "" } },
{ "pid": 1, "tid": 1, "ts": 23543890.625, "dur": 13984.6000671387, "ph": "X", "name": "ValidateTokens", "args": { "durationMS": 13.9846000671387, "detail": "" } },
{ "pid": 1, "tid": 1, "ts": 23869501.953125, "dur": 3153187.25585938, "ph": "X", "name": "Write COM Callable Wrappers", "args": { "durationMS": 3153.18725585938, "detail": "" } },
{ "pid": 1, "tid": 1, "ts": 26484427.734375, "dur": 81100.4028320313, "ph": "X", "name": "Collect implemented projected interfaces by COM Callable Wrappers", "args": { "durationMS": 81.1004028320313, "detail": "" } },
{ "pid": 1, "tid": 1, "ts": 27022691.40625, "dur": 3622403.56445313, "ph": "X", "name": "Metadata", "args": { "durationMS": 3622.40356445313, "detail": "Global" } },
{ "pid": 1, "tid": 1, "ts": 27072464.84375, "dur": 498970.428466797, "ph": "X", "name": "Attributes", "args": { "durationMS": 498.970428466797, "detail": "" } },
{ "pid": 1, "tid": 1, "ts": 28010947.265625, "dur": 579268.005371094, "ph": "X", "name": "WriteCodeRegistration", "args": { "durationMS": 579.268005371094, "detail": "" } },
{ "pid": 1, "tid": 1, "ts": 28051986.328125, "dur": 4494.50016021729, "ph": "X", "name": "GenericContextCollector", "args": { "durationMS": 4.49450016021729, "detail": "Collect" } },
{ "pid": 1, "tid": 1, "ts": 28182292.96875, "dur": 2791.30005836487, "ph": "X", "name": "ReversePInvokerWrapperTable", "args": { "durationMS": 2.79130005836487, "detail": "Il2CppReversePInvokeWrapperTable.cpp" } },
{ "pid": 1, "tid": 1, "ts": 28185384.765625, "dur": 276294.097900391, "ph": "X", "name": "GenericMethodPointerTable", "args": { "durationMS": 276.294097900391, "detail": "Il2CppGenericMethodPointerTable.cpp" } },
{ "pid": 1, "tid": 1, "ts": 28461943.359375, "dur": 75288.8031005859, "ph": "X", "name": "InvokerTable", "args": { "durationMS": 75.2888031005859, "detail": "Il2CppInvokerTable.cpp" } },
{ "pid": 1, "tid": 1, "ts": 28538138.671875, "dur": 49083.9996337891, "ph": "X", "name": "InteropDataTable", "args": { "durationMS": 49.0839996337891, "detail": "Il2CppInteropDataTable.cpp" } },
{ "pid": 1, "tid": 1, "ts": 28590214.84375, "dur": 2054877.44140625, "ph": "X", "name": "WriteMetadata", "args": { "durationMS": 2054.87744140625, "detail": "" } },
{ "pid": 1, "tid": 1, "ts": 28744283.203125, "dur": 11716.0997390747, "ph": "X", "name": "Metadata", "args": { "durationMS": 11.7160997390747, "detail": "Collect string literals" } },
{ "pid": 1, "tid": 1, "ts": 28944269.53125, "dur": 161491.500854492, "ph": "X", "name": "GenericClasses", "args": { "durationMS": 161.491500854492, "detail": "" } },
{ "pid": 1, "tid": 1, "ts": 29105759.765625, "dur": 36054.5997619629, "ph": "X", "name": "GenericInst2", "args": { "durationMS": 36.0545997619629, "detail": "" } },
{ "pid": 1, "tid": 1, "ts": 29141814.453125, "dur": 680014.465332031, "ph": "X", "name": "GenericMethods", "args": { "durationMS": 680.014465332031, "detail": "" } },
{ "pid": 1, "tid": 1, "ts": 29821830.078125, "dur": 284812.5, "ph": "X", "name": "Il2CppTypes", "args": { "durationMS": 284.8125, "detail": "" } },
{ "pid": 1, "tid": 1, "ts": 30106642.578125, "dur": 212376.495361328, "ph": "X", "name": "GenericMethods", "args": { "durationMS": 212.376495361328, "detail": "" } },
{ "pid": 1, "tid": 1, "ts": 30319021.484375, "dur": 144153.198242188, "ph": "X", "name": "CompilerCalculateTypeValues", "args": { "durationMS": 144.153198242188, "detail": "" } },
{ "pid": 1, "tid": 1, "ts": 30463173.828125, "dur": 2340.3000831604, "ph": "X", "name": "Registration", "args": { "durationMS": 2.3403000831604, "detail": "" } },
{ "pid": 1, "tid": 1, "ts": 30465835.9375, "dur": 4935.29987335205, "ph": "X", "name": "StringLiteralWriter", "args": { "durationMS": 4.93529987335205, "detail": "" } },
{ "pid": 1, "tid": 1, "ts": 30470949.21875, "dur": 555.299997329712, "ph": "X", "name": "Metadata Strings", "args": { "durationMS": 0.555299997329712, "detail": "" } },
{ "pid": 1, "tid": 1, "ts": 30471507.8125, "dur": 1826.59995555878, "ph": "X", "name": "Events", "args": { "durationMS": 1.82659995555878, "detail": "" } },
{ "pid": 1, "tid": 1, "ts": 30473332.03125, "dur": 6247.79987335205, "ph": "X", "name": "Properties", "args": { "durationMS": 6.24779987335205, "detail": "" } },
{ "pid": 1, "tid": 1, "ts": 30479582.03125, "dur": 66272.9034423828, "ph": "X", "name": "Methods", "args": { "durationMS": 66.2729034423828, "detail": "" } },
{ "pid": 1, "tid": 1, "ts": 30545851.5625, "dur": 865.000009536743, "ph": "X", "name": "Parameter Default Values", "args": { "durationMS": 0.865000009536743, "detail": "" } },
{ "pid": 1, "tid": 1, "ts": 30546718.75, "dur": 1584.2000246048, "ph": "X", "name": "Field Default Values", "args": { "durationMS": 1.5842000246048, "detail": "" } },
{ "pid": 1, "tid": 1, "ts": 30548304.6875, "dur": 1606.40001296997, "ph": "X", "name": "Field and Parameter Default Values Data", "args": { "durationMS": 1.60640001296997, "detail": "" } },
{ "pid": 1, "tid": 1, "ts": 30549912.109375, "dur": 514.100015163422, "ph": "X", "name": "Field Marshaled Sizes", "args": { "durationMS": 0.514100015163422, "detail": "" } },
{ "pid": 1, "tid": 1, "ts": 30550425.78125, "dur": 15293.9004898071, "ph": "X", "name": "Parameters", "args": { "durationMS": 15.2939004898071, "detail": "" } },
{ "pid": 1, "tid": 1, "ts": 30565722.65625, "dur": 9512.70008087158, "ph": "X", "name": "Fields", "args": { "durationMS": 9.51270008087158, "detail": "" } },
{ "pid": 1, "tid": 1, "ts": 30575230.46875, "dur": 1248.90005588531, "ph": "X", "name": "Generic Parameters", "args": { "durationMS": 1.24890005588531, "detail": "" } },
{ "pid": 1, "tid": 1, "ts": 30576482.421875, "dur": 346.89998626709, "ph": "X", "name": "Generic Parameter Constraints", "args": { "durationMS": 0.34689998626709, "detail": "" } },
{ "pid": 1, "tid": 1, "ts": 30576830.078125, "dur": 1129.40001487732, "ph": "X", "name": "Generic Containers", "args": { "durationMS": 1.12940001487732, "detail": "" } },
{ "pid": 1, "tid": 1, "ts": 30578289.0625, "dur": 341.100007295609, "ph": "X", "name": "Interfaces", "args": { "durationMS": 0.341100007295609, "detail": "" } },
{ "pid": 1, "tid": 1, "ts": 30578625, "dur": 1226.50003433228, "ph": "X", "name": "VTables", "args": { "durationMS": 1.22650003433228, "detail": "" } },
{ "pid": 1, "tid": 1, "ts": 30579855.46875, "dur": 760.800004005432, "ph": "X", "name": "Interface Offsets", "args": { "durationMS": 0.760800004005432, "detail": "" } },
{ "pid": 1, "tid": 1, "ts": 30580615.234375, "dur": 44629.7988891602, "ph": "X", "name": "Type Definitions", "args": { "durationMS": 44.6297988891602, "detail": "" } },
{ "pid": 1, "tid": 1, "ts": 30625244.140625, "dur": 6302.80017852783, "ph": "X", "name": "Images", "args": { "durationMS": 6.30280017852783, "detail": "" } },
{ "pid": 1, "tid": 1, "ts": 30631548.828125, "dur": 1606.89997673035, "ph": "X", "name": "Assemblies", "args": { "durationMS": 1.60689997673035, "detail": "" } },
{ "pid": 1, "tid": 1, "ts": 30633154.296875, "dur": 1050.60005187988, "ph": "X", "name": "Metadata Usage Lists", "args": { "durationMS": 1.05060005187988, "detail": "" } },
{ "pid": 1, "tid": 1, "ts": 30634207.03125, "dur": 3579.79989051819, "ph": "X", "name": "Metadata Usage Pairs", "args": { "durationMS": 3.57979989051819, "detail": "" } },
{ "pid": 1, "tid": 1, "ts": 30638021.484375, "dur": 345.299988985062, "ph": "X", "name": "Referenced Assemblies", "args": { "durationMS": 0.345299988985062, "detail": "" } },
{ "pid": 1, "tid": 1, "ts": 30638369.140625, "dur": 1279.00004386902, "ph": "X", "name": "Attribute Types Ranges", "args": { "durationMS": 1.27900004386902, "detail": "" } },
{ "pid": 1, "tid": 1, "ts": 30639650.390625, "dur": 491.499990224838, "ph": "X", "name": "Attribute Types", "args": { "durationMS": 0.491499990224838, "detail": "" } },
{ "pid": 1, "tid": 1, "ts": 30640445.3125, "dur": 790.199995040894, "ph": "X", "name": "Unresolved Virtual Call Parameter Ranges", "args": { "durationMS": 0.790199995040894, "detail": "" } },
{ "pid": 1, "tid": 1, "ts": 30641236.328125, "dur": 782.500028610229, "ph": "X", "name": "Windows Runtime type names", "args": { "durationMS": 0.782500028610229, "detail": "" } },
{ "pid": 1, "tid": 1, "ts": 30642019.53125, "dur": 1282.0999622345, "ph": "X", "name": "Exported Types", "args": { "durationMS": 1.2820999622345, "detail": "" } }
],
"meta_datetime": "09/16/2019 21:37:58",
"meta_command_line": "\"C:\\Program Files\\Unity\\Hub\\Editor\\2019.2.5f1\\Editor\\Data\\il2cpp/build/il2cpp.exe\" --convert-to-cpp --emit-null-checks --enable-array-bounds-check --dotnetprofile=\"unityaot\" --profiler-report --map-file-parser=\"C:/Program Files/Unity/Hub/Editor/2019.2.5f1/Editor/Data/Tools/MapFileParser/MapFileParser.exe\" --directory=C:/Users/subdiox/Documents/FlickInput/Temp/StagingArea/Data/Managed --generatedcppdir=C:/Users/subdiox/Documents/FlickInput/Temp/StagingArea/Il2CppOutputProject/Source/il2cppOutput ",
"meta_command_line_args": "C:\\Program Files\\Unity\\Hub\\Editor\\2019.2.5f1\\Editor\\Data\\il2cpp/build/il2cpp.exe --convert-to-cpp --emit-null-checks --enable-array-bounds-check --dotnetprofile=unityaot --profiler-report --map-file-parser=C:/Program Files/Unity/Hub/Editor/2019.2.5f1/Editor/Data/Tools/MapFileParser/MapFileParser.exe --directory=C:/Users/subdiox/Documents/FlickInput/Temp/StagingArea/Data/Managed --generatedcppdir=C:/Users/subdiox/Documents/FlickInput/Temp/StagingArea/Il2CppOutputProject/Source/il2cppOutput",
"meta_user_name": "subdiox",
"meta_os_version": "Microsoft Windows NT 6.2.9200.0",
"meta_cpu_count": "16"}
